osxstrap/__init__.py
osxstrap/__main__.py
osxstrap/ansible.py
osxstrap/common.py
osxstrap/osxstrap.py
osxstrap/output.py
osxstrap/ansible/ansible.cfg
osxstrap/ansible/inventory
osxstrap/ansible/playbook.yml
osxstrap/ansible/requirements.yml
osxstrap-0.0.32.dist-info/DESCRIPTION.rst
osxstrap-0.0.32.dist-info/METADATA
osxstrap-0.0.32.dist-info/RECORD
osxstrap-0.0.32.dist-info/WHEEL
osxstrap-0.0.32.dist-info/entry_points.txt
osxstrap-0.0.32.dist-info/metadata.json
osxstrap-0.0.32.dist-info/top_level.txt
